{
  "last_updated": "2026-06-19T12:05:22Z",
  "run_number": 82,
  "data_source": "10d simulation (trades_10d.csv, 965 trades) — bot offline Day 62.50, no live trades",
  "avg_slippage": "UNKNOWN — no live trades (bot offline Day 62.50)",
  "noise_stop_problem": "87% early SL hits (<2h) in non-trending regimes [cached, last live session Apr 19 — 62.50d stale]",
  "data_available": false,
  "trades_csv_present": false,
  "findings": [
    {
      "severity": "HIGH",
      "finding": "Trailing stop mean exit: +$8.86/trade (152 exits). TP2 mean: +$71.10/trade (145 exits). Gap: $62.24/trade = $9,460 foregone EV across 152 trailing exits in 10d sim.",
      "root_cause": "Trailing stop activates at TP1 with near-breakeven floor. Reversal after TP1 catches trailing stop before meaningful extension toward TP2.",
      "proposed_fix": "Lock 70% of TP1 gain as trailing floor in position_manager.py:_update_trailing_stop (line 1244-1251). Change `entry + fee_buffer` to `entry + (tp1-entry) * 0.70` for LONG; `entry - (entry-tp1) * 0.70` for SHORT.",
      "code_file": "bot/execution/position_manager.py",
      "code_line": 1244,
      "env_var_suggestion": "TRAILING_MIN_LOCK_PCT=0.70",
      "confidence": 0.88,
      "expected_impact": "+$9,460 per 10d sim period (152 trades x $62.24 avg improvement)",
      "status": "PENDING_CODE_CHANGE — requires paper trading validation before deploy"
    },
    {
      "severity": "HIGH",
      "finding": "SL rate 38.3% (370/965 trades). Avg SL loss: -$224.63. Total SL drag: -$83,113 per 10d sim. System earns +$0.94/trade net — fragile margin, sensitive to WR drift.",
      "root_cause": "SL hit rate may indicate too-tight stops relative to current market noise.",
      "proposed_fix": "Monitor SL hit rate post-restart. If SL% > 40% over 50 live trades, increase ATR multiplier by 10%.",
      "confidence": 0.72,
      "status": "MONITOR_POST_RESTART"
    },
    {
      "severity": "MEDIUM",
      "finding": "BTC SHORT 70-79% conf: -$91.87/trade, 98 trades. Rule btc_short_conf70_80_penalize_v1 at gate=100% active. Needs live verification post-restart (times_applied=3, times_correct=0).",
      "confidence": 0.90,
      "status": "RULE_ACTIVE_NEEDS_LIVE_VERIFICATION"
    }
  ],
  "close_reason_breakdown": {
    "SL": {"count": 370, "rate": 0.383, "avg_pnl": -224.63, "total_pnl": -83113},
    "TP1": {"count": 297, "rate": 0.308, "avg_pnl": 243.84, "total_pnl": 72420},
    "TP2": {"count": 145, "rate": 0.150, "avg_pnl": 71.10, "total_pnl": 10310},
    "TRAILING_STOP": {"count": 152, "rate": 0.157, "avg_pnl": 8.86, "total_pnl": 1347}
  },
  "trailing_stop_detail": {
    "avg_pnl_trailing": 8.86,
    "avg_pnl_tp2": 71.10,
    "count_trailing": 152,
    "count_tp2": 145,
    "ev_gap_per_trade": 62.24,
    "ev_gap_total": 9460.0,
    "proposed_lock_pct": 0.70,
    "fix_file": "bot/execution/position_manager.py",
    "fix_line": 1244
  },
  "noise_regime_active_rules": [
    "illiquid_regime_penalize_v1 (gate=100, conf=0.78)",
    "ranging_regime_penalize_v1 (gate=50, conf=0.76)",
    "night_session_block_v1 (gate=100, conf=0.88)"
  ]
}
